[
    {
        "time_updated": "Apr 28, 2022 09:53:00 UTC",
        "time_updatedISO": "2022-04-28T09:53:00+00:00",
        "time_updateduk": "Apr 28, 2022 at 10:53 BST",
        "disclaimer": "This data was produced from the CoinDesk Bitcoin Price Index (USD). Non-USD currency data converted using hourly conversion rate from openexchangerates.org",
        "chartName": "Bitcoin",
        "bpi_USD_code": "USD",
        "bpi_USD_symbol": "&#36;",
        "bpi_USD_rate": "39,783.3433",
        "bpi_USD_description": "United States Dollar",
        "bpi_USD_rate_float": 39783.3433,
        "bpi_GBP_code": "GBP",
        "bpi_GBP_symbol": "&pound;",
        "bpi_GBP_rate": "31,734.2977",
        "bpi_GBP_description": "British Pound Sterling",
        "bpi_GBP_rate_float": 31734.2977,
        "bpi_EUR_code": "EUR",
        "bpi_EUR_symbol": "&euro;",
        "bpi_EUR_rate": "37,831.2542",
        "bpi_EUR_description": "Euro",
        "bpi_EUR_rate_float": 37831.2542,
        "bpi_CNY_code": "CNY",
        "bpi_CNY_symbol": "&yen;",
        "bpi_CNY_rate": "40,202.5000",
        "bpi_CNY_description": "Chinese Yuan",
        "bpi_CNY_rate_float": 40202.5
    },
    {
        "USD_PHP": 52.323501
    }
]