[
    {
        "time_updated": "Jan 27, 2022 07:41:00 UTC",
        "time_updatedISO": "2022-01-27T07:41:00+00:00",
        "time_updateduk": "Jan 27, 2022 at 07:41 GMT",
        "disclaimer": "This data was produced from the CoinDesk Bitcoin Price Index (USD). Non-USD currency data converted using hourly conversion rate from openexchangerates.org",
        "chartName": "Bitcoin",
        "bpi_USD_code": "USD",
        "bpi_USD_symbol": "&#36;",
        "bpi_USD_rate": "36,244.0583",
        "bpi_USD_description": "United States Dollar",
        "bpi_USD_rate_float": 36244.0583,
        "bpi_GBP_code": "GBP",
        "bpi_GBP_symbol": "&pound;",
        "bpi_GBP_rate": "26,991.9651",
        "bpi_GBP_description": "British Pound Sterling",
        "bpi_GBP_rate_float": 26991.9651,
        "bpi_EUR_code": "EUR",
        "bpi_EUR_symbol": "&euro;",
        "bpi_EUR_rate": "32,305.7065",
        "bpi_EUR_description": "Euro",
        "bpi_EUR_rate_float": 32305.7065,
        "bpi_CNY_code": "CNY",
        "bpi_CNY_symbol": "&yen;",
        "bpi_CNY_rate": "40,202.5000",
        "bpi_CNY_description": "Chinese Yuan",
        "bpi_CNY_rate_float": 40202.5
    },
    {
        "USD_PHP": 51.334498
    }
]