{"time":{"updated":"Jul 23, 2024 22:26:21 UTC","updatedISO":"2024-07-23T22:26:21+00:00","updateduk":"Jul 23, 2024 at 23:26 BST"},"disclaimer":"This data was produced from the CoinDesk Bitcoin Price Index (USD). Non-USD currency data converted using hourly conversion rate from openexchangerates.org","chartName":"Bitcoin","bpi":{"USD":{"code":"USD","symbol":"&#36;","rate":"65,905.867","description":"United States Dollar","rate_float":65905.8674},"GBP":{"code":"GBP","symbol":"&pound;","rate":"51,058.462","description":"British Pound Sterling","rate_float":51058.4618},"EUR":{"code":"EUR","symbol":"&euro;","rate":"60,717.692","description":"Euro","rate_float":60717.6916},"CNY":{"code":"CNY","symbol":"&yen;","rate":"479,478.367","description":"Chinese Yuan","rate_float":479478.3665}}}