{"time":{"updated":"Mar 29, 2024 23:39:47 UTC","updatedISO":"2024-03-29T23:39:47+00:00","updateduk":"Mar 29, 2024 at 23:39 GMT"},"disclaimer":"This data was produced from the CoinDesk Bitcoin Price Index (USD). Non-USD currency data converted using hourly conversion rate from openexchangerates.org","chartName":"Bitcoin","bpi":{"USD":{"code":"USD","symbol":"&#36;","rate":"70,022.356","description":"United States Dollar","rate_float":70022.3563},"GBP":{"code":"GBP","symbol":"&pound;","rate":"55,458.827","description":"British Pound Sterling","rate_float":55458.8266},"EUR":{"code":"EUR","symbol":"&euro;","rate":"64,834.89","description":"Euro","rate_float":64834.8901},"CNY":{"code":"CNY","symbol":"&yen;","rate":"505,645.439","description":"Chinese Yuan","rate_float":505645.4394}}}