{"time":{"updated":"Jan 18, 2024 09:27:10 UTC","updatedISO":"2024-01-18T09:27:10+00:00","updateduk":"Jan 18, 2024 at 09:27 GMT"},"disclaimer":"This data was produced from the CoinDesk Bitcoin Price Index (USD). Non-USD currency data converted using hourly conversion rate from openexchangerates.org","chartName":"Bitcoin","bpi":{"USD":{"code":"USD","symbol":"&#36;","rate":"42,798.38","description":"United States Dollar","rate_float":42798.3801},"GBP":{"code":"GBP","symbol":"&pound;","rate":"33,729.874","description":"British Pound Sterling","rate_float":33729.8741},"EUR":{"code":"EUR","symbol":"&euro;","rate":"39,337.96","description":"Euro","rate_float":39337.9598},"CNY":{"code":"CNY","symbol":"&yen;","rate":"304,771.544","description":"Chinese Yuan","rate_float":304771.5442}}}