{"time":{"updated":"Apr 2, 2024 14:09:26 UTC","updatedISO":"2024-04-02T14:09:26+00:00","updateduk":"Apr 2, 2024 at 15:09 BST"},"disclaimer":"This data was produced from the CoinDesk Bitcoin Price Index (USD). Non-USD currency data converted using hourly conversion rate from openexchangerates.org","chartName":"Bitcoin","bpi":{"USD":{"code":"USD","symbol":"&#36;","rate":"65,435.658","description":"United States Dollar","rate_float":65435.6576},"GBP":{"code":"GBP","symbol":"&pound;","rate":"52,111.911","description":"British Pound Sterling","rate_float":52111.9107},"EUR":{"code":"EUR","symbol":"&euro;","rate":"60,874.269","description":"Euro","rate_float":60874.2687},"CNY":{"code":"CNY","symbol":"&yen;","rate":"473,485.875","description":"Chinese Yuan","rate_float":473485.8745}}}