{"time":{"updated":"Oct 11, 2024 15:56:59 UTC","updatedISO":"2024-10-11T15:56:59+00:00","updateduk":"Oct 11, 2024 at 16:56 BST"},"disclaimer":"This data was produced from the CoinDesk Bitcoin Price Index (USD). Non-USD currency data converted using hourly conversion rate from openexchangerates.org","chartName":"Bitcoin","bpi":{"USD":{"code":"USD","symbol":"&#36;","rate":"62,421.635","description":"United States Dollar","rate_float":62421.6347},"GBP":{"code":"GBP","symbol":"&pound;","rate":"47,744.81","description":"British Pound Sterling","rate_float":47744.8102},"EUR":{"code":"EUR","symbol":"&euro;","rate":"57,042.013","description":"Euro","rate_float":57042.0133},"CNY":{"code":"CNY","symbol":"&yen;","rate":"441,089.997","description":"Chinese Yuan","rate_float":441089.997}}}