{"time":{"updated":"Oct 5, 2024 23:26:56 UTC","updatedISO":"2024-10-05T23:26:56+00:00","updateduk":"Oct 6, 2024 at 00:26 BST"},"disclaimer":"This data was produced from the CoinDesk Bitcoin Price Index (USD). Non-USD currency data converted using hourly conversion rate from openexchangerates.org","chartName":"Bitcoin","bpi":{"USD":{"code":"USD","symbol":"&#36;","rate":"62,006.886","description":"United States Dollar","rate_float":62006.8859},"GBP":{"code":"GBP","symbol":"&pound;","rate":"47,255.944","description":"British Pound Sterling","rate_float":47255.9438},"EUR":{"code":"EUR","symbol":"&euro;","rate":"56,462.292","description":"Euro","rate_float":56462.2921},"CNY":{"code":"CNY","symbol":"&yen;","rate":"437,123.743","description":"Chinese Yuan","rate_float":437123.7425}}}