{"time":{"updated":"May 17, 2024 23:43:51 UTC","updatedISO":"2024-05-17T23:43:51+00:00","updateduk":"May 18, 2024 at 00:43 BST"},"disclaimer":"This data was produced from the CoinDesk Bitcoin Price Index (USD). Non-USD currency data converted using hourly conversion rate from openexchangerates.org","chartName":"Bitcoin","bpi":{"USD":{"code":"USD","symbol":"&#36;","rate":"67,022.649","description":"United States Dollar","rate_float":67022.6489},"GBP":{"code":"GBP","symbol":"&pound;","rate":"52,752.991","description":"British Pound Sterling","rate_float":52752.9907},"EUR":{"code":"EUR","symbol":"&euro;","rate":"61,603.868","description":"Euro","rate_float":61603.8677},"CNY":{"code":"CNY","symbol":"&yen;","rate":"484,144.806","description":"Chinese Yuan","rate_float":484144.8063}}}