{"time":{"updated":"May 31, 2024 15:26:58 UTC","updatedISO":"2024-05-31T15:26:58+00:00","updateduk":"May 31, 2024 at 16:26 BST"},"disclaimer":"This data was produced from the CoinDesk Bitcoin Price Index (USD). Non-USD currency data converted using hourly conversion rate from openexchangerates.org","chartName":"Bitcoin","bpi":{"USD":{"code":"USD","symbol":"&#36;","rate":"67,521.695","description":"United States Dollar","rate_float":67521.6946},"GBP":{"code":"GBP","symbol":"&pound;","rate":"53,036.941","description":"British Pound Sterling","rate_float":53036.9407},"EUR":{"code":"EUR","symbol":"&euro;","rate":"62,198.419","description":"Euro","rate_float":62198.4193},"CNY":{"code":"CNY","symbol":"&yen;","rate":"479,728.136","description":"Chinese Yuan","rate_float":479728.1361}}}