{"time":{"updated":"Jan 23, 2024 11:21:36 UTC","updatedISO":"2024-01-23T11:21:36+00:00","updateduk":"Jan 23, 2024 at 11:21 GMT"},"disclaimer":"This data was produced from the CoinDesk Bitcoin Price Index (USD). Non-USD currency data converted using hourly conversion rate from openexchangerates.org","chartName":"Bitcoin","bpi":{"USD":{"code":"USD","symbol":"&#36;","rate":"38,950.584","description":"United States Dollar","rate_float":38950.5837},"GBP":{"code":"GBP","symbol":"&pound;","rate":"30,601.643","description":"British Pound Sterling","rate_float":30601.6429},"EUR":{"code":"EUR","symbol":"&euro;","rate":"35,775.098","description":"Euro","rate_float":35775.0984},"CNY":{"code":"CNY","symbol":"&yen;","rate":"276,288.175","description":"Chinese Yuan","rate_float":276288.1753}}}