{"time":{"updated":"Oct 28, 2022 11:12:00 UTC","updatedISO":"2022-10-28T11:12:00+00:00","updateduk":"Oct 28, 2022 at 12:12 BST"},"disclaimer":"This data was produced from the CoinDesk Bitcoin Price Index (USD). Non-USD currency data converted using hourly conversion rate from openexchangerates.org","chartName":"Bitcoin","bpi":{"USD":{"code":"USD","symbol":"&#36;","rate":"20,139.3044","description":"United States Dollar","rate_float":20139.3044},"GBP":{"code":"GBP","symbol":"&pound;","rate":"16,828.2417","description":"British Pound Sterling","rate_float":16828.2417},"EUR":{"code":"EUR","symbol":"&euro;","rate":"19,618.6228","description":"Euro","rate_float":19618.6228},"CNY":{"code":"CNY","symbol":"&yen;","rate":"40,202.5000","description":"Chinese Yuan","rate_float":40202.5}}}