{"time":{"updated":"Aug 6, 2024 03:45:53 UTC","updatedISO":"2024-08-06T03:45:53+00:00","updateduk":"Aug 6, 2024 at 04:45 BST"},"disclaimer":"This data was produced from the CoinDesk Bitcoin Price Index (USD). Non-USD currency data converted using hourly conversion rate from openexchangerates.org","chartName":"Bitcoin","bpi":{"USD":{"code":"USD","symbol":"&#36;","rate":"55,769.629","description":"United States Dollar","rate_float":55769.6292},"GBP":{"code":"GBP","symbol":"&pound;","rate":"43,627.298","description":"British Pound Sterling","rate_float":43627.2982},"EUR":{"code":"EUR","symbol":"&euro;","rate":"50,921.854","description":"Euro","rate_float":50921.8542},"CNY":{"code":"CNY","symbol":"&yen;","rate":"398,022.267","description":"Chinese Yuan","rate_float":398022.2668}}}