{"time":{"updated":"Mar 13, 2024 00:46:33 UTC","updatedISO":"2024-03-13T00:46:33+00:00","updateduk":"Mar 13, 2024 at 00:46 GMT"},"disclaimer":"This data was produced from the CoinDesk Bitcoin Price Index (USD). Non-USD currency data converted using hourly conversion rate from openexchangerates.org","chartName":"Bitcoin","bpi":{"USD":{"code":"USD","symbol":"&#36;","rate":"71,583.009","description":"United States Dollar","rate_float":71583.009},"GBP":{"code":"GBP","symbol":"&pound;","rate":"55,945.844","description":"British Pound Sterling","rate_float":55945.8438},"EUR":{"code":"EUR","symbol":"&euro;","rate":"65,510.909","description":"Euro","rate_float":65510.9086},"CNY":{"code":"CNY","symbol":"&yen;","rate":"514,109.17","description":"Chinese Yuan","rate_float":514109.1703}}}