{"time":{"updated":"Dec 17, 2021 03:16:00 UTC","updatedISO":"2021-12-17T03:16:00+00:00","updateduk":"Dec 17, 2021 at 03:16 GMT"},"disclaimer":"This data was produced from the CoinDesk Bitcoin Price Index (USD). Non-USD currency data converted using hourly conversion rate from openexchangerates.org","chartName":"Bitcoin","bpi":{"USD":{"code":"USD","symbol":"&#36;","rate":"47,730.4558","description":"United States Dollar","rate_float":47730.4558},"GBP":{"code":"GBP","symbol":"&pound;","rate":"35,815.4066","description":"British Pound Sterling","rate_float":35815.4066},"EUR":{"code":"EUR","symbol":"&euro;","rate":"42,140.5034","description":"Euro","rate_float":42140.5034},"CNY":{"code":"CNY","symbol":"&yen;","rate":"40,202.5000","description":"Chinese Yuan","rate_float":40202.5}}}