{"time":{"updated":"Dec 14, 2024 03:43:56 UTC","updatedISO":"2024-12-14T03:43:56+00:00","updateduk":"Dec 14, 2024 at 03:43 GMT"},"disclaimer":"This data was produced from the CoinDesk Bitcoin Price Index (USD). Non-USD currency data converted using hourly conversion rate from openexchangerates.org","chartName":"Bitcoin","bpi":{"USD":{"code":"USD","symbol":"&#36;","rate":"102,477.104","description":"United States Dollar","rate_float":102477.1038},"GBP":{"code":"GBP","symbol":"&pound;","rate":"80,185.567","description":"British Pound Sterling","rate_float":80185.5669},"EUR":{"code":"EUR","symbol":"&euro;","rate":"97,307.134","description":"Euro","rate_float":97307.1339},"CNY":{"code":"CNY","symbol":"&yen;","rate":"742,928.26","description":"Chinese Yuan","rate_float":742928.2595}}}