{"time":{"updated":"Sep 16, 2024 04:52:24 UTC","updatedISO":"2024-09-16T04:52:24+00:00","updateduk":"Sep 16, 2024 at 05:52 BST"},"disclaimer":"This data was produced from the CoinDesk Bitcoin Price Index (USD). Non-USD currency data converted using hourly conversion rate from openexchangerates.org","chartName":"Bitcoin","bpi":{"USD":{"code":"USD","symbol":"&#36;","rate":"58,392.891","description":"United States Dollar","rate_float":58392.8908},"GBP":{"code":"GBP","symbol":"&pound;","rate":"44,371.824","description":"British Pound Sterling","rate_float":44371.8235},"EUR":{"code":"EUR","symbol":"&euro;","rate":"52,587.645","description":"Euro","rate_float":52587.6448},"CNY":{"code":"CNY","symbol":"&yen;","rate":"414,209.971","description":"Chinese Yuan","rate_float":414209.9712}}}