{"time":{"updated":"Apr 23, 2024 11:06:53 UTC","updatedISO":"2024-04-23T11:06:53+00:00","updateduk":"Apr 23, 2024 at 12:06 BST"},"disclaimer":"This data was produced from the CoinDesk Bitcoin Price Index (USD). Non-USD currency data converted using hourly conversion rate from openexchangerates.org","chartName":"Bitcoin","bpi":{"USD":{"code":"USD","symbol":"&#36;","rate":"66,112.078","description":"United States Dollar","rate_float":66112.0777},"GBP":{"code":"GBP","symbol":"&pound;","rate":"53,487.58","description":"British Pound Sterling","rate_float":53487.5798},"EUR":{"code":"EUR","symbol":"&euro;","rate":"62,023.112","description":"Euro","rate_float":62023.1118},"CNY":{"code":"CNY","symbol":"&yen;","rate":"479,120.838","description":"Chinese Yuan","rate_float":479120.8383}}}