{"time":{"updated":"Oct 4, 2024 11:37:31 UTC","updatedISO":"2024-10-04T11:37:31+00:00","updateduk":"Oct 4, 2024 at 12:37 BST"},"disclaimer":"This data was produced from the CoinDesk Bitcoin Price Index (USD). Non-USD currency data converted using hourly conversion rate from openexchangerates.org","chartName":"Bitcoin","bpi":{"USD":{"code":"USD","symbol":"&#36;","rate":"61,340.741","description":"United States Dollar","rate_float":61340.7409},"GBP":{"code":"GBP","symbol":"&pound;","rate":"46,592.709","description":"British Pound Sterling","rate_float":46592.7093},"EUR":{"code":"EUR","symbol":"&euro;","rate":"55,625.133","description":"Euro","rate_float":55625.1334},"CNY":{"code":"CNY","symbol":"&yen;","rate":"432,403.151","description":"Chinese Yuan","rate_float":432403.1509}}}