{"time":{"updated":"Apr 7, 2024 21:32:20 UTC","updatedISO":"2024-04-07T21:32:20+00:00","updateduk":"Apr 7, 2024 at 22:32 BST"},"disclaimer":"This data was produced from the CoinDesk Bitcoin Price Index (USD). Non-USD currency data converted using hourly conversion rate from openexchangerates.org","chartName":"Bitcoin","bpi":{"USD":{"code":"USD","symbol":"&#36;","rate":"69,355.868","description":"United States Dollar","rate_float":69355.8677},"GBP":{"code":"GBP","symbol":"&pound;","rate":"54,912.924","description":"British Pound Sterling","rate_float":54912.9244},"EUR":{"code":"EUR","symbol":"&euro;","rate":"63,991.191","description":"Euro","rate_float":63991.1914},"CNY":{"code":"CNY","symbol":"&yen;","rate":"496,044.54","description":"Chinese Yuan","rate_float":496044.5403}}}