{"time":{"updated":"Jan 14, 2022 14:15:00 UTC","updatedISO":"2022-01-14T14:15:00+00:00","updateduk":"Jan 14, 2022 at 14:15 GMT"},"disclaimer":"This data was produced from the CoinDesk Bitcoin Price Index (USD). Non-USD currency data converted using hourly conversion rate from openexchangerates.org","chartName":"Bitcoin","bpi":{"USD":{"code":"USD","symbol":"&#36;","rate":"42,372.9583","description":"United States Dollar","rate_float":42372.9583},"GBP":{"code":"GBP","symbol":"&pound;","rate":"30,927.9375","description":"British Pound Sterling","rate_float":30927.9375},"EUR":{"code":"EUR","symbol":"&euro;","rate":"37,045.2368","description":"Euro","rate_float":37045.2368},"CNY":{"code":"CNY","symbol":"&yen;","rate":"40,202.5000","description":"Chinese Yuan","rate_float":40202.5}}}