{"time":{"updated":"Aug 25, 2024 20:18:20 UTC","updatedISO":"2024-08-25T20:18:20+00:00","updateduk":"Aug 25, 2024 at 21:18 BST"},"disclaimer":"This data was produced from the CoinDesk Bitcoin Price Index (USD). Non-USD currency data converted using hourly conversion rate from openexchangerates.org","chartName":"Bitcoin","bpi":{"USD":{"code":"USD","symbol":"&#36;","rate":"64,178.652","description":"United States Dollar","rate_float":64178.652},"GBP":{"code":"GBP","symbol":"&pound;","rate":"48,555.835","description":"British Pound Sterling","rate_float":48555.8353},"EUR":{"code":"EUR","symbol":"&euro;","rate":"57,338.235","description":"Euro","rate_float":57338.2346},"CNY":{"code":"CNY","symbol":"&yen;","rate":"457,150.956","description":"Chinese Yuan","rate_float":457150.9563}}}