{"time":{"updated":"Nov 25, 2024 11:07:48 UTC","updatedISO":"2024-11-25T11:07:48+00:00","updateduk":"Nov 25, 2024 at 11:07 GMT"},"disclaimer":"This data was produced from the CoinDesk Bitcoin Price Index (USD). Non-USD currency data converted using hourly conversion rate from openexchangerates.org","chartName":"Bitcoin","bpi":{"USD":{"code":"USD","symbol":"&#36;","rate":"98,552.498","description":"United States Dollar","rate_float":98552.4976},"GBP":{"code":"GBP","symbol":"&pound;","rate":"78,377.816","description":"British Pound Sterling","rate_float":78377.8158},"EUR":{"code":"EUR","symbol":"&euro;","rate":"93,953.348","description":"Euro","rate_float":93953.3482},"CNY":{"code":"CNY","symbol":"&yen;","rate":"714,209.95","description":"Chinese Yuan","rate_float":714209.9498}}}