{"time":{"updated":"May 25, 2024 08:30:16 UTC","updatedISO":"2024-05-25T08:30:16+00:00","updateduk":"May 25, 2024 at 09:30 BST"},"disclaimer":"This data was produced from the CoinDesk Bitcoin Price Index (USD). Non-USD currency data converted using hourly conversion rate from openexchangerates.org","chartName":"Bitcoin","bpi":{"USD":{"code":"USD","symbol":"&#36;","rate":"69,027.09","description":"United States Dollar","rate_float":69027.0903},"GBP":{"code":"GBP","symbol":"&pound;","rate":"54,172.875","description":"British Pound Sterling","rate_float":54172.8747},"EUR":{"code":"EUR","symbol":"&euro;","rate":"63,598.938","description":"Euro","rate_float":63598.938},"CNY":{"code":"CNY","symbol":"&yen;","rate":"490,858.542","description":"Chinese Yuan","rate_float":490858.5421}}}