{"time":{"updated":"Jun 28, 2024 16:52:53 UTC","updatedISO":"2024-06-28T16:52:53+00:00","updateduk":"Jun 28, 2024 at 17:52 BST"},"disclaimer":"This data was produced from the CoinDesk Bitcoin Price Index (USD). Non-USD currency data converted using hourly conversion rate from openexchangerates.org","chartName":"Bitcoin","bpi":{"USD":{"code":"USD","symbol":"&#36;","rate":"60,758.763","description":"United States Dollar","rate_float":60758.7625},"GBP":{"code":"GBP","symbol":"&pound;","rate":"48,079.867","description":"British Pound Sterling","rate_float":48079.867},"EUR":{"code":"EUR","symbol":"&euro;","rate":"56,724.441","description":"Euro","rate_float":56724.4414},"CNY":{"code":"CNY","symbol":"&yen;","rate":"441,546.079","description":"Chinese Yuan","rate_float":441546.0786}}}