{"time":{"updated":"Sep 19, 2024 12:28:53 UTC","updatedISO":"2024-09-19T12:28:53+00:00","updateduk":"Sep 19, 2024 at 13:28 BST"},"disclaimer":"This data was produced from the CoinDesk Bitcoin Price Index (USD). Non-USD currency data converted using hourly conversion rate from openexchangerates.org","chartName":"Bitcoin","bpi":{"USD":{"code":"USD","symbol":"&#36;","rate":"62,911.689","description":"United States Dollar","rate_float":62911.6888},"GBP":{"code":"GBP","symbol":"&pound;","rate":"47,409.997","description":"British Pound Sterling","rate_float":47409.997},"EUR":{"code":"EUR","symbol":"&euro;","rate":"56,320.557","description":"Euro","rate_float":56320.557},"CNY":{"code":"CNY","symbol":"&yen;","rate":"444,439.625","description":"Chinese Yuan","rate_float":444439.6254}}}