{"time":{"updated":"Feb 28, 2022 06:37:00 UTC","updatedISO":"2022-02-28T06:37:00+00:00","updateduk":"Feb 28, 2022 at 06:37 GMT"},"disclaimer":"This data was produced from the CoinDesk Bitcoin Price Index (USD). Non-USD currency data converted using hourly conversion rate from openexchangerates.org","chartName":"Bitcoin","bpi":{"USD":{"code":"USD","symbol":"&#36;","rate":"37,835.1058","description":"United States Dollar","rate_float":37835.1058},"GBP":{"code":"GBP","symbol":"&pound;","rate":"28,315.7931","description":"British Pound Sterling","rate_float":28315.7931},"EUR":{"code":"EUR","symbol":"&euro;","rate":"33,913.1565","description":"Euro","rate_float":33913.1565},"CNY":{"code":"CNY","symbol":"&yen;","rate":"40,202.5000","description":"Chinese Yuan","rate_float":40202.5}}}