{"time":{"updated":"Jan 11, 2025 13:37:00 UTC","updatedISO":"2025-01-11T13:37:00+00:00","updateduk":"Jan 11, 2025 at 13:37 GMT"},"disclaimer":"This data was produced from the CoinDesk Bitcoin Price Index (USD). Non-USD currency data converted using hourly conversion rate from openexchangerates.org","chartName":"Bitcoin","bpi":{"USD":{"code":"USD","symbol":"&#36;","rate":"95,701.697","description":"United States Dollar","rate_float":95701.6972},"GBP":{"code":"GBP","symbol":"&pound;","rate":"76,329.281","description":"British Pound Sterling","rate_float":76329.2812},"EUR":{"code":"EUR","symbol":"&euro;","rate":"92,039.576","description":"Euro","rate_float":92039.5761},"CNY":{"code":"CNY","symbol":"&yen;","rate":"701,292.467","description":"Chinese Yuan","rate_float":701292.4671}}}