{"time":{"updated":"Sep 9, 2024 11:24:34 UTC","updatedISO":"2024-09-09T11:24:34+00:00","updateduk":"Sep 9, 2024 at 12:24 BST"},"disclaimer":"This data was produced from the CoinDesk Bitcoin Price Index (USD). Non-USD currency data converted using hourly conversion rate from openexchangerates.org","chartName":"Bitcoin","bpi":{"USD":{"code":"USD","symbol":"&#36;","rate":"55,270.944","description":"United States Dollar","rate_float":55270.9439},"GBP":{"code":"GBP","symbol":"&pound;","rate":"42,223.409","description":"British Pound Sterling","rate_float":42223.4085},"EUR":{"code":"EUR","symbol":"&euro;","rate":"49,990.911","description":"Euro","rate_float":49990.9106},"CNY":{"code":"CNY","symbol":"&yen;","rate":"393,219.603","description":"Chinese Yuan","rate_float":393219.6033}}}