{"time":{"updated":"May 1, 2024 09:33:06 UTC","updatedISO":"2024-05-01T09:33:06+00:00","updateduk":"May 1, 2024 at 10:33 BST"},"disclaimer":"This data was produced from the CoinDesk Bitcoin Price Index (USD). Non-USD currency data converted using hourly conversion rate from openexchangerates.org","chartName":"Bitcoin","bpi":{"USD":{"code":"USD","symbol":"&#36;","rate":"57,288.267","description":"United States Dollar","rate_float":57288.2669},"GBP":{"code":"GBP","symbol":"&pound;","rate":"45,837.946","description":"British Pound Sterling","rate_float":45837.9464},"EUR":{"code":"EUR","symbol":"&euro;","rate":"53,693.715","description":"Euro","rate_float":53693.7146},"CNY":{"code":"CNY","symbol":"&yen;","rate":"414,824.341","description":"Chinese Yuan","rate_float":414824.3408}}}