{"time":{"updated":"Oct 13, 2024 17:36:46 UTC","updatedISO":"2024-10-13T17:36:46+00:00","updateduk":"Oct 13, 2024 at 18:36 BST"},"disclaimer":"This data was produced from the CoinDesk Bitcoin Price Index (USD). Non-USD currency data converted using hourly conversion rate from openexchangerates.org","chartName":"Bitcoin","bpi":{"USD":{"code":"USD","symbol":"&#36;","rate":"62,627.471","description":"United States Dollar","rate_float":62627.4714},"GBP":{"code":"GBP","symbol":"&pound;","rate":"47,920.6","description":"British Pound Sterling","rate_float":47920.5997},"EUR":{"code":"EUR","symbol":"&euro;","rate":"57,222.783","description":"Euro","rate_float":57222.7833},"CNY":{"code":"CNY","symbol":"&yen;","rate":"442,538.238","description":"Chinese Yuan","rate_float":442538.2384}}}