{"time":{"updated":"Aug 30, 2024 16:57:36 UTC","updatedISO":"2024-08-30T16:57:36+00:00","updateduk":"Aug 30, 2024 at 17:57 BST"},"disclaimer":"This data was produced from the CoinDesk Bitcoin Price Index (USD). Non-USD currency data converted using hourly conversion rate from openexchangerates.org","chartName":"Bitcoin","bpi":{"USD":{"code":"USD","symbol":"&#36;","rate":"58,574.785","description":"United States Dollar","rate_float":58574.7854},"GBP":{"code":"GBP","symbol":"&pound;","rate":"44,588.65","description":"British Pound Sterling","rate_float":44588.6496},"EUR":{"code":"EUR","symbol":"&euro;","rate":"52,963.672","description":"Euro","rate_float":52963.6724},"CNY":{"code":"CNY","symbol":"&yen;","rate":"415,306.944","description":"Chinese Yuan","rate_float":415306.9435}}}