{"time":{"updated":"Dec 7, 2024 04:52:47 UTC","updatedISO":"2024-12-07T04:52:47+00:00","updateduk":"Dec 7, 2024 at 04:52 GMT"},"disclaimer":"This data was produced from the CoinDesk Bitcoin Price Index (USD). Non-USD currency data converted using hourly conversion rate from openexchangerates.org","chartName":"Bitcoin","bpi":{"USD":{"code":"USD","symbol":"&#36;","rate":"99,718.254","description":"United States Dollar","rate_float":99718.2542},"GBP":{"code":"GBP","symbol":"&pound;","rate":"78,241.036","description":"British Pound Sterling","rate_float":78241.0363},"EUR":{"code":"EUR","symbol":"&euro;","rate":"94,290.689","description":"Euro","rate_float":94290.6893},"CNY":{"code":"CNY","symbol":"&yen;","rate":"724,981.624","description":"Chinese Yuan","rate_float":724981.6235}}}