{"time":{"updated":"Nov 11, 2024 21:24:50 UTC","updatedISO":"2024-11-11T21:24:50+00:00","updateduk":"Nov 11, 2024 at 21:24 GMT"},"disclaimer":"This data was produced from the CoinDesk Bitcoin Price Index (USD). Non-USD currency data converted using hourly conversion rate from openexchangerates.org","chartName":"Bitcoin","bpi":{"USD":{"code":"USD","symbol":"&#36;","rate":"87,577.583","description":"United States Dollar","rate_float":87577.5833},"GBP":{"code":"GBP","symbol":"&pound;","rate":"68,061.97","description":"British Pound Sterling","rate_float":68061.9698},"EUR":{"code":"EUR","symbol":"&euro;","rate":"82,189.898","description":"Euro","rate_float":82189.8979},"CNY":{"code":"CNY","symbol":"&yen;","rate":"631,810.959","description":"Chinese Yuan","rate_float":631810.959}}}