{"time":{"updated":"Sep 17, 2021 20:49:00 UTC","updatedISO":"2021-09-17T20:49:00+00:00","updateduk":"Sep 17, 2021 at 21:49 BST"},"disclaimer":"This data was produced from the CoinDesk Bitcoin Price Index (USD). Non-USD currency data converted using hourly conversion rate from openexchangerates.org","chartName":"Bitcoin","bpi":{"USD":{"code":"USD","symbol":"&#36;","rate":"47,148.1733","description":"United States Dollar","rate_float":47148.1733},"GBP":{"code":"GBP","symbol":"&pound;","rate":"34,324.1059","description":"British Pound Sterling","rate_float":34324.1059},"EUR":{"code":"EUR","symbol":"&euro;","rate":"40,191.8847","description":"Euro","rate_float":40191.8847},"CNY":{"code":"CNY","symbol":"&yen;","rate":"40,202.5000","description":"Chinese Yuan","rate_float":40202.5}}}