{"time":{"updated":"Nov 29, 2024 07:33:05 UTC","updatedISO":"2024-11-29T07:33:05+00:00","updateduk":"Nov 29, 2024 at 07:33 GMT"},"disclaimer":"This data was produced from the CoinDesk Bitcoin Price Index (USD). Non-USD currency data converted using hourly conversion rate from openexchangerates.org","chartName":"Bitcoin","bpi":{"USD":{"code":"USD","symbol":"&#36;","rate":"95,997.164","description":"United States Dollar","rate_float":95997.1642},"GBP":{"code":"GBP","symbol":"&pound;","rate":"75,444.843","description":"British Pound Sterling","rate_float":75444.8434},"EUR":{"code":"EUR","symbol":"&euro;","rate":"90,732.872","description":"Euro","rate_float":90732.8717},"CNY":{"code":"CNY","symbol":"&yen;","rate":"694,318.69","description":"Chinese Yuan","rate_float":694318.6898}}}