{"time":{"updated":"May 14, 2024 19:58:15 UTC","updatedISO":"2024-05-14T19:58:15+00:00","updateduk":"May 14, 2024 at 20:58 BST"},"disclaimer":"This data was produced from the CoinDesk Bitcoin Price Index (USD). Non-USD currency data converted using hourly conversion rate from openexchangerates.org","chartName":"Bitcoin","bpi":{"USD":{"code":"USD","symbol":"&#36;","rate":"61,603.376","description":"United States Dollar","rate_float":61603.3764},"GBP":{"code":"GBP","symbol":"&pound;","rate":"48,933.841","description":"British Pound Sterling","rate_float":48933.8412},"EUR":{"code":"EUR","symbol":"&euro;","rate":"56,926.818","description":"Euro","rate_float":56926.8177},"CNY":{"code":"CNY","symbol":"&yen;","rate":"445,614.183","description":"Chinese Yuan","rate_float":445614.1834}}}