{"time":{"updated":"Jan 27, 2025 18:53:37 UTC","updatedISO":"2025-01-27T18:53:37+00:00","updateduk":"Jan 27, 2025 at 18:53 GMT"},"disclaimer":"This data was produced from the CoinDesk Bitcoin Price Index (USD). Non-USD currency data converted using hourly conversion rate from openexchangerates.org","chartName":"Bitcoin","bpi":{"USD":{"code":"USD","symbol":"&#36;","rate":"98,994.22","description":"United States Dollar","rate_float":98994.2203},"GBP":{"code":"GBP","symbol":"&pound;","rate":"79,500.971","description":"British Pound Sterling","rate_float":79500.9714},"EUR":{"code":"EUR","symbol":"&euro;","rate":"94,646.097","description":"Euro","rate_float":94646.0971},"CNY":{"code":"CNY","symbol":"&yen;","rate":"719,361.3","description":"Chinese Yuan","rate_float":719361.3004}}}