{"time":{"updated":"Aug 5, 2024 08:21:52 UTC","updatedISO":"2024-08-05T08:21:52+00:00","updateduk":"Aug 5, 2024 at 09:21 BST"},"disclaimer":"This data was produced from the CoinDesk Bitcoin Price Index (USD). Non-USD currency data converted using hourly conversion rate from openexchangerates.org","chartName":"Bitcoin","bpi":{"USD":{"code":"USD","symbol":"&#36;","rate":"52,867.676","description":"United States Dollar","rate_float":52867.6763},"GBP":{"code":"GBP","symbol":"&pound;","rate":"41,318.098","description":"British Pound Sterling","rate_float":41318.098},"EUR":{"code":"EUR","symbol":"&euro;","rate":"48,285.106","description":"Euro","rate_float":48285.1061},"CNY":{"code":"CNY","symbol":"&yen;","rate":"377,306.032","description":"Chinese Yuan","rate_float":377306.0324}}}