{"time":{"updated":"Dec 21, 2024 22:10:47 UTC","updatedISO":"2024-12-21T22:10:47+00:00","updateduk":"Dec 21, 2024 at 22:10 GMT"},"disclaimer":"This data was produced from the CoinDesk Bitcoin Price Index (USD). Non-USD currency data converted using hourly conversion rate from openexchangerates.org","chartName":"Bitcoin","bpi":{"USD":{"code":"USD","symbol":"&#36;","rate":"96,704.106","description":"United States Dollar","rate_float":96704.1063},"GBP":{"code":"GBP","symbol":"&pound;","rate":"77,340.076","description":"British Pound Sterling","rate_float":77340.0761},"EUR":{"code":"EUR","symbol":"&euro;","rate":"93,138.819","description":"Euro","rate_float":93138.8193},"CNY":{"code":"CNY","symbol":"&yen;","rate":"705,862.613","description":"Chinese Yuan","rate_float":705862.6128}}}