{"time":{"updated":"Sep 19, 2024 18:20:24 UTC","updatedISO":"2024-09-19T18:20:24+00:00","updateduk":"Sep 19, 2024 at 19:20 BST"},"disclaimer":"This data was produced from the CoinDesk Bitcoin Price Index (USD). Non-USD currency data converted using hourly conversion rate from openexchangerates.org","chartName":"Bitcoin","bpi":{"USD":{"code":"USD","symbol":"&#36;","rate":"63,580.803","description":"United States Dollar","rate_float":63580.8033},"GBP":{"code":"GBP","symbol":"&pound;","rate":"47,871.322","description":"British Pound Sterling","rate_float":47871.322},"EUR":{"code":"EUR","symbol":"&euro;","rate":"56,994.786","description":"Euro","rate_float":56994.7858},"CNY":{"code":"CNY","symbol":"&yen;","rate":"449,389.117","description":"Chinese Yuan","rate_float":449389.1174}}}