{"time":{"updated":"Mar 31, 2022 10:53:00 UTC","updatedISO":"2022-03-31T10:53:00+00:00","updateduk":"Mar 31, 2022 at 11:53 BST"},"disclaimer":"This data was produced from the CoinDesk Bitcoin Price Index (USD). Non-USD currency data converted using hourly conversion rate from openexchangerates.org","chartName":"Bitcoin","bpi":{"USD":{"code":"USD","symbol":"&#36;","rate":"47,232.1483","description":"United States Dollar","rate_float":47232.1483},"GBP":{"code":"GBP","symbol":"&pound;","rate":"35,995.2424","description":"British Pound Sterling","rate_float":35995.2424},"EUR":{"code":"EUR","symbol":"&euro;","rate":"42,506.2885","description":"Euro","rate_float":42506.2885},"CNY":{"code":"CNY","symbol":"&yen;","rate":"40,202.5000","description":"Chinese Yuan","rate_float":40202.5}}}