{"time":{"updated":"Dec 31, 2024 23:14:55 UTC","updatedISO":"2024-12-31T23:14:55+00:00","updateduk":"Dec 31, 2024 at 23:14 GMT"},"disclaimer":"This data was produced from the CoinDesk Bitcoin Price Index (USD). Non-USD currency data converted using hourly conversion rate from openexchangerates.org","chartName":"Bitcoin","bpi":{"USD":{"code":"USD","symbol":"&#36;","rate":"93,985.909","description":"United States Dollar","rate_float":93985.909},"GBP":{"code":"GBP","symbol":"&pound;","rate":"74,951.883","description":"British Pound Sterling","rate_float":74951.8827},"EUR":{"code":"EUR","symbol":"&euro;","rate":"90,167.356","description":"Euro","rate_float":90167.3555},"CNY":{"code":"CNY","symbol":"&yen;","rate":"685,965.556","description":"Chinese Yuan","rate_float":685965.5556}}}