{"time":{"updated":"May 5, 2024 08:33:11 UTC","updatedISO":"2024-05-05T08:33:11+00:00","updateduk":"May 5, 2024 at 09:33 BST"},"disclaimer":"This data was produced from the CoinDesk Bitcoin Price Index (USD). Non-USD currency data converted using hourly conversion rate from openexchangerates.org","chartName":"Bitcoin","bpi":{"USD":{"code":"USD","symbol":"&#36;","rate":"63,792.731","description":"United States Dollar","rate_float":63792.7311},"GBP":{"code":"GBP","symbol":"&pound;","rate":"50,838.979","description":"British Pound Sterling","rate_float":50838.9791},"EUR":{"code":"EUR","symbol":"&euro;","rate":"59,216.496","description":"Euro","rate_float":59216.4958},"CNY":{"code":"CNY","symbol":"&yen;","rate":"461,680.754","description":"Chinese Yuan","rate_float":461680.7537}}}