{"time":{"updated":"Mar 13, 2024 02:55:40 UTC","updatedISO":"2024-03-13T02:55:40+00:00","updateduk":"Mar 13, 2024 at 02:55 GMT"},"disclaimer":"This data was produced from the CoinDesk Bitcoin Price Index (USD). Non-USD currency data converted using hourly conversion rate from openexchangerates.org","chartName":"Bitcoin","bpi":{"USD":{"code":"USD","symbol":"&#36;","rate":"72,019.384","description":"United States Dollar","rate_float":72019.384},"GBP":{"code":"GBP","symbol":"&pound;","rate":"56,296.4","description":"British Pound Sterling","rate_float":56296.4001},"EUR":{"code":"EUR","symbol":"&euro;","rate":"65,927.696","description":"Euro","rate_float":65927.6964},"CNY":{"code":"CNY","symbol":"&yen;","rate":"517,560.101","description":"Chinese Yuan","rate_float":517560.1009}}}