{"time":{"updated":"May 11, 2024 09:42:30 UTC","updatedISO":"2024-05-11T09:42:30+00:00","updateduk":"May 11, 2024 at 10:42 BST"},"disclaimer":"This data was produced from the CoinDesk Bitcoin Price Index (USD). Non-USD currency data converted using hourly conversion rate from openexchangerates.org","chartName":"Bitcoin","bpi":{"USD":{"code":"USD","symbol":"&#36;","rate":"60,844.473","description":"United States Dollar","rate_float":60844.4727},"GBP":{"code":"GBP","symbol":"&pound;","rate":"48,582.304","description":"British Pound Sterling","rate_float":48582.3036},"EUR":{"code":"EUR","symbol":"&euro;","rate":"56,448.46","description":"Euro","rate_float":56448.4596},"CNY":{"code":"CNY","symbol":"&yen;","rate":"439,710.836","description":"Chinese Yuan","rate_float":439710.8356}}}