{"time":{"updated":"Nov 29, 2024 17:11:17 UTC","updatedISO":"2024-11-29T17:11:17+00:00","updateduk":"Nov 29, 2024 at 17:11 GMT"},"disclaimer":"This data was produced from the CoinDesk Bitcoin Price Index (USD). Non-USD currency data converted using hourly conversion rate from openexchangerates.org","chartName":"Bitcoin","bpi":{"USD":{"code":"USD","symbol":"&#36;","rate":"97,432.327","description":"United States Dollar","rate_float":97432.3268},"GBP":{"code":"GBP","symbol":"&pound;","rate":"76,669.79","description":"British Pound Sterling","rate_float":76669.7903},"EUR":{"code":"EUR","symbol":"&euro;","rate":"92,254.383","description":"Euro","rate_float":92254.3832},"CNY":{"code":"CNY","symbol":"&yen;","rate":"705,663.37","description":"Chinese Yuan","rate_float":705663.3701}}}