{"time":{"updated":"Aug 22, 2024 04:14:19 UTC","updatedISO":"2024-08-22T04:14:19+00:00","updateduk":"Aug 22, 2024 at 05:14 BST"},"disclaimer":"This data was produced from the CoinDesk Bitcoin Price Index (USD). Non-USD currency data converted using hourly conversion rate from openexchangerates.org","chartName":"Bitcoin","bpi":{"USD":{"code":"USD","symbol":"&#36;","rate":"60,538.803","description":"United States Dollar","rate_float":60538.8028},"GBP":{"code":"GBP","symbol":"&pound;","rate":"46,265.569","description":"British Pound Sterling","rate_float":46265.5692},"EUR":{"code":"EUR","symbol":"&euro;","rate":"54,331.033","description":"Euro","rate_float":54331.0328},"CNY":{"code":"CNY","symbol":"&yen;","rate":"431,847.496","description":"Chinese Yuan","rate_float":431847.4955}}}