{"time":{"updated":"Sep 18, 2024 06:59:20 UTC","updatedISO":"2024-09-18T06:59:20+00:00","updateduk":"Sep 18, 2024 at 07:59 BST"},"disclaimer":"This data was produced from the CoinDesk Bitcoin Price Index (USD). Non-USD currency data converted using hourly conversion rate from openexchangerates.org","chartName":"Bitcoin","bpi":{"USD":{"code":"USD","symbol":"&#36;","rate":"60,456.781","description":"United States Dollar","rate_float":60456.7806},"GBP":{"code":"GBP","symbol":"&pound;","rate":"45,943.586","description":"British Pound Sterling","rate_float":45943.5863},"EUR":{"code":"EUR","symbol":"&euro;","rate":"54,364.49","description":"Euro","rate_float":54364.4903},"CNY":{"code":"CNY","symbol":"&yen;","rate":"429,019.452","description":"Chinese Yuan","rate_float":429019.452}}}