{"time":{"updated":"May 24, 2024 09:58:31 UTC","updatedISO":"2024-05-24T09:58:31+00:00","updateduk":"May 24, 2024 at 10:58 BST"},"disclaimer":"This data was produced from the CoinDesk Bitcoin Price Index (USD). Non-USD currency data converted using hourly conversion rate from openexchangerates.org","chartName":"Bitcoin","bpi":{"USD":{"code":"USD","symbol":"&#36;","rate":"67,451.083","description":"United States Dollar","rate_float":67451.0825},"GBP":{"code":"GBP","symbol":"&pound;","rate":"53,089.263","description":"British Pound Sterling","rate_float":53089.2631},"EUR":{"code":"EUR","symbol":"&euro;","rate":"62,309.287","description":"Euro","rate_float":62309.2865},"CNY":{"code":"CNY","symbol":"&yen;","rate":"479,523.236","description":"Chinese Yuan","rate_float":479523.2358}}}