{"time":{"updated":"Dec 27, 2024 09:42:27 UTC","updatedISO":"2024-12-27T09:42:27+00:00","updateduk":"Dec 27, 2024 at 09:42 GMT"},"disclaimer":"This data was produced from the CoinDesk Bitcoin Price Index (USD). Non-USD currency data converted using hourly conversion rate from openexchangerates.org","chartName":"Bitcoin","bpi":{"USD":{"code":"USD","symbol":"&#36;","rate":"96,982.76","description":"United States Dollar","rate_float":96982.7595},"GBP":{"code":"GBP","symbol":"&pound;","rate":"77,341.811","description":"British Pound Sterling","rate_float":77341.811},"EUR":{"code":"EUR","symbol":"&euro;","rate":"93,042.447","description":"Euro","rate_float":93042.4469},"CNY":{"code":"CNY","symbol":"&yen;","rate":"707,838.368","description":"Chinese Yuan","rate_float":707838.3683}}}