{"time":{"updated":"Jan 19, 2022 02:39:00 UTC","updatedISO":"2022-01-19T02:39:00+00:00","updateduk":"Jan 19, 2022 at 02:39 GMT"},"disclaimer":"This data was produced from the CoinDesk Bitcoin Price Index (USD). Non-USD currency data converted using hourly conversion rate from openexchangerates.org","chartName":"Bitcoin","bpi":{"USD":{"code":"USD","symbol":"&#36;","rate":"42,401.0200","description":"United States Dollar","rate_float":42401.02},"GBP":{"code":"GBP","symbol":"&pound;","rate":"31,174.5867","description":"British Pound Sterling","rate_float":31174.5867},"EUR":{"code":"EUR","symbol":"&euro;","rate":"37,449.8105","description":"Euro","rate_float":37449.8105},"CNY":{"code":"CNY","symbol":"&yen;","rate":"40,202.5000","description":"Chinese Yuan","rate_float":40202.5}}}