{"time":{"updated":"Sep 16, 2024 17:49:12 UTC","updatedISO":"2024-09-16T17:49:12+00:00","updateduk":"Sep 16, 2024 at 18:49 BST"},"disclaimer":"This data was produced from the CoinDesk Bitcoin Price Index (USD). Non-USD currency data converted using hourly conversion rate from openexchangerates.org","chartName":"Bitcoin","bpi":{"USD":{"code":"USD","symbol":"&#36;","rate":"58,010.026","description":"United States Dollar","rate_float":58010.0261},"GBP":{"code":"GBP","symbol":"&pound;","rate":"43,923.394","description":"British Pound Sterling","rate_float":43923.3935},"EUR":{"code":"EUR","symbol":"&euro;","rate":"52,125.663","description":"Euro","rate_float":52125.6631},"CNY":{"code":"CNY","symbol":"&yen;","rate":"411,494.12","description":"Chinese Yuan","rate_float":411494.1203}}}