{"time":{"updated":"Aug 18, 2024 04:52:01 UTC","updatedISO":"2024-08-18T04:52:01+00:00","updateduk":"Aug 18, 2024 at 05:52 BST"},"disclaimer":"This data was produced from the CoinDesk Bitcoin Price Index (USD). Non-USD currency data converted using hourly conversion rate from openexchangerates.org","chartName":"Bitcoin","bpi":{"USD":{"code":"USD","symbol":"&#36;","rate":"59,507.024","description":"United States Dollar","rate_float":59507.0239},"GBP":{"code":"GBP","symbol":"&pound;","rate":"45,974.472","description":"British Pound Sterling","rate_float":45974.4721},"EUR":{"code":"EUR","symbol":"&euro;","rate":"53,942.82","description":"Euro","rate_float":53942.8197},"CNY":{"code":"CNY","symbol":"&yen;","rate":"426,367.827","description":"Chinese Yuan","rate_float":426367.8266}}}