{"time":{"updated":"Dec 19, 2024 08:56:11 UTC","updatedISO":"2024-12-19T08:56:11+00:00","updateduk":"Dec 19, 2024 at 08:56 GMT"},"disclaimer":"This data was produced from the CoinDesk Bitcoin Price Index (USD). Non-USD currency data converted using hourly conversion rate from openexchangerates.org","chartName":"Bitcoin","bpi":{"USD":{"code":"USD","symbol":"&#36;","rate":"102,919.126","description":"United States Dollar","rate_float":102919.1256},"GBP":{"code":"GBP","symbol":"&pound;","rate":"80,531.437","description":"British Pound Sterling","rate_float":80531.4369},"EUR":{"code":"EUR","symbol":"&euro;","rate":"97,726.856","description":"Euro","rate_float":97726.8557},"CNY":{"code":"CNY","symbol":"&yen;","rate":"746,132.785","description":"Chinese Yuan","rate_float":746132.7846}}}