{"time":{"updated":"May 29, 2023 17:37:00 UTC","updatedISO":"2023-05-29T17:37:00+00:00","updateduk":"May 29, 2023 at 18:37 BST"},"disclaimer":"This data was produced from the CoinDesk Bitcoin Price Index (USD). Non-USD currency data converted using hourly conversion rate from openexchangerates.org","chartName":"Bitcoin","bpi":{"USD":{"code":"USD","symbol":"&#36;","rate":"27,643.9568","description":"United States Dollar","rate_float":27643.9568},"GBP":{"code":"GBP","symbol":"&pound;","rate":"23,099.0692","description":"British Pound Sterling","rate_float":23099.0692},"EUR":{"code":"EUR","symbol":"&euro;","rate":"26,929.2500","description":"Euro","rate_float":26929.25},"CNY":{"code":"CNY","symbol":"&yen;","rate":"40,202.5000","description":"Chinese Yuan","rate_float":40202.5}}}