{"time":{"updated":"Nov 11, 2021 02:43:00 UTC","updatedISO":"2021-11-11T02:43:00+00:00","updateduk":"Nov 11, 2021 at 02:43 GMT"},"disclaimer":"This data was produced from the CoinDesk Bitcoin Price Index (USD). Non-USD currency data converted using hourly conversion rate from openexchangerates.org","chartName":"Bitcoin","bpi":{"USD":{"code":"USD","symbol":"&#36;","rate":"64,246.9544","description":"United States Dollar","rate_float":64246.9544},"GBP":{"code":"GBP","symbol":"&pound;","rate":"47,922.3173","description":"British Pound Sterling","rate_float":47922.3173},"EUR":{"code":"EUR","symbol":"&euro;","rate":"55,966.6785","description":"Euro","rate_float":55966.6785},"CNY":{"code":"CNY","symbol":"&yen;","rate":"40,202.5000","description":"Chinese Yuan","rate_float":40202.5}}}