{
    "time_updated": "Sep 18, 2022 13:01:00 UTC",
    "time_updatedISO": "2022-09-18T13:01:00+00:00",
    "time_updateduk": "Sep 18, 2022 at 14:01 BST",
    "disclaimer": "This data was produced from the CoinDesk Bitcoin Price Index (USD). Non-USD currency data converted using hourly conversion rate from openexchangerates.org",
    "chartName": "Bitcoin",
    "bpi_USD_code": "USD",
    "bpi_USD_symbol": "&#36;",
    "bpi_USD_rate": "20,009.1902",
    "bpi_USD_description": "United States Dollar",
    "bpi_USD_rate_float": 20009.1902,
    "bpi_GBP_code": "GBP",
    "bpi_GBP_symbol": "&pound;",
    "bpi_GBP_rate": "16,719.5192",
    "bpi_GBP_description": "British Pound Sterling",
    "bpi_GBP_rate_float": 16719.5192,
    "bpi_EUR_code": "EUR",
    "bpi_EUR_symbol": "&euro;",
    "bpi_EUR_rate": "19,491.8725",
    "bpi_EUR_description": "Euro",
    "bpi_EUR_rate_float": 19491.8725,
    "bpi_CNY_code": "CNY",
    "bpi_CNY_symbol": "&yen;",
    "bpi_CNY_rate": "40,202.5000",
    "bpi_CNY_description": "Chinese Yuan",
    "bpi_CNY_rate_float": 40202.5,
    "USD_PHP": 57.010375
}