{
    "time_updated": "Jan 12, 2022 22:48:00 UTC",
    "time_updatedISO": "2022-01-12T22:48:00+00:00",
    "time_updateduk": "Jan 12, 2022 at 22:48 GMT",
    "disclaimer": "This data was produced from the CoinDesk Bitcoin Price Index (USD). Non-USD currency data converted using hourly conversion rate from openexchangerates.org",
    "chartName": "Bitcoin",
    "bpi_USD_code": "USD",
    "bpi_USD_symbol": "&#36;",
    "bpi_USD_rate": "43,871.2883",
    "bpi_USD_description": "United States Dollar",
    "bpi_USD_rate_float": 43871.2883,
    "bpi_GBP_code": "GBP",
    "bpi_GBP_symbol": "&pound;",
    "bpi_GBP_rate": "32,021.2585",
    "bpi_GBP_description": "British Pound Sterling",
    "bpi_GBP_rate_float": 32021.2585,
    "bpi_EUR_code": "EUR",
    "bpi_EUR_symbol": "&euro;",
    "bpi_EUR_rate": "38,342.2337",
    "bpi_EUR_description": "Euro",
    "bpi_EUR_rate_float": 38342.2337,
    "bpi_CNY_code": "CNY",
    "bpi_CNY_symbol": "&yen;",
    "bpi_CNY_rate": "40,202.5000",
    "bpi_CNY_description": "Chinese Yuan",
    "bpi_CNY_rate_float": 40202.5,
    "USD_PHP": 51.001504
}